my_app/__init__.py
my_app/audio.py
my_app/main.py
my_app/responses.py
my_app/transcription.py
mohamedboualamallah_fiji_ai-0.1.0.dist-info/METADATA
mohamedboualamallah_fiji_ai-0.1.0.dist-info/WHEEL
mohamedboualamallah_fiji_ai-0.1.0.dist-info/entry_points.txt
mohamedboualamallah_fiji_ai-0.1.0.dist-info/top_level.txt
mohamedboualamallah_fiji_ai-0.1.0.dist-info/RECORD
