Metadata-Version: 2.4
Name: mohamedboualamallah_fiji-ai
Version: 0.1.0
Summary: A modular application for audio processing and Finch robot control.
Author: Mohamed Boualamallah
Author-email: mohamedboualamallah@icloud.com
Requires-Dist: sounddevice
Requires-Dist: numpy
Requires-Dist: webrtcvad
Requires-Dist: scipy
Requires-Dist: gradio-client
Requires-Dist: google-genai
Requires-Dist: playsound
Requires-Dist: BirdBrain
Dynamic: author
Dynamic: author-email
Dynamic: requires-dist
Dynamic: summary
